strongbus/__init__.py
strongbus/core.py
strongbus/py.typed
strongbus/test_core.py
strongbus-0.1.2.dist-info/METADATA
strongbus-0.1.2.dist-info/WHEEL
strongbus-0.1.2.dist-info/entry_points.txt
strongbus-0.1.2.dist-info/RECORD
