Metadata-Version: 2.4
Name: strongbus
Version: 0.1.2
Summary: A type-safe event bus library for Python that provides reliable publish-subscribe messaging with automatic memory management, full type safety, and global event subscriptions for cross-cutting concerns like logging.
Project-URL: Repository, https://github.com/elmcrest/strongbus
Author-email: Marius Räsener <marius@raesener.de>
Keywords: event-bus,events,pubsub,type-safe,typed
Requires-Python: >=3.10
Provides-Extra: dev
Requires-Dist: build; extra == 'dev'
Requires-Dist: pytest-cov>=6.2.1; extra == 'dev'
Requires-Dist: tox; extra == 'dev'
